stormspans/__init__.py
stormspans/database.py
stormspans/expr.py
stormspans/properties.py
stormspans/variables.py
StormSpans-1.0.0.dist-info/LICENSE
StormSpans-1.0.0.dist-info/METADATA
StormSpans-1.0.0.dist-info/WHEEL
StormSpans-1.0.0.dist-info/top_level.txt
StormSpans-1.0.0.dist-info/RECORD
