Metadata-Version: 2.1
Name: StormSpans
Version: 1.0.0
Summary: PostgreSQL range type support for Canonical's Storm ORM using Spans 
Home-page: https://www.github.com/runfalk/stormspans
Author: Andreas Runfalk
Author-email: andreas@runfalk.se
License: MIT
Platform: UNKNOWN
Classifier: Development Status :: 3 - Alpha
Classifier: Intended Audience :: Developers
Classifier: License :: OSI Approved :: MIT License
Classifier: Programming Language :: Python :: 2.7
Classifier: Programming Language :: Python :: 3.4
Classifier: Programming Language :: Python :: 3.5
Classifier: Programming Language :: Python :: 3.6
Classifier: Programming Language :: Python :: 3.7
Classifier: Topic :: Database
Classifier: Topic :: Database :: Front-Ends
Requires-Dist: spans
Requires-Dist: psycospans
Provides-Extra: dev
Requires-Dist: psycopg2-binary; extra == 'dev'
Requires-Dist: pytest; extra == 'dev'
Requires-Dist: storm-legacy; extra == 'dev'
